deepbridge/__init__.py
deepbridge/cli/__init__.py
deepbridge/cli/commands.py
deepbridge/cli/utils.py
deepbridge/config/__init__.py
deepbridge/config/settings.py
deepbridge/core/__init__.py
deepbridge/core/base_processor.py
deepbridge/core/db_data.py
deepbridge/core/experiment/__init__.py
deepbridge/core/experiment/data_manager.py
deepbridge/core/experiment/dependencies.py
deepbridge/core/experiment/experiment.py
deepbridge/core/experiment/interfaces.py
deepbridge/core/experiment/manager_factory.py
deepbridge/core/experiment/managers/__init__.py
deepbridge/core/experiment/managers/base_manager.py
deepbridge/core/experiment/managers/hyperparameter_manager.py
deepbridge/core/experiment/managers/model_manager.py
deepbridge/core/experiment/managers/resilience_manager.py
deepbridge/core/experiment/managers/robustness_manager.py
deepbridge/core/experiment/managers/uncertainty_manager.py
deepbridge/core/experiment/model_evaluation.py
deepbridge/core/experiment/model_result.py
deepbridge/core/experiment/parameter_standards.py
deepbridge/core/experiment/report/EXAMPLES_PHASE4.md
deepbridge/core/experiment/report/__init__.py
deepbridge/core/experiment/report/adapters/__init__.py
deepbridge/core/experiment/report/adapters/base.py
deepbridge/core/experiment/report/adapters/html_adapter.py
deepbridge/core/experiment/report/adapters/json_adapter.py
deepbridge/core/experiment/report/adapters/markdown_adapter.py
deepbridge/core/experiment/report/adapters/pdf_adapter.py
deepbridge/core/experiment/report/asset_manager.py
deepbridge/core/experiment/report/asset_processor.py
deepbridge/core/experiment/report/asset_processor_old.py
deepbridge/core/experiment/report/async_generator.py
deepbridge/core/experiment/report/base.py
deepbridge/core/experiment/report/cache/__init__.py
deepbridge/core/experiment/report/cache/base.py
deepbridge/core/experiment/report/cache/cache_manager.py
deepbridge/core/experiment/report/cache/memory_cache.py
deepbridge-0.1.60.dist-info/METADATA
deepbridge-0.1.60.dist-info/WHEEL
deepbridge-0.1.60.dist-info/RECORD
