Metadata-Version: 2.3
Name: deepbridge
Version: 0.1.60
Summary: DeepBridge: Framework for ML Model Validation and Knowledge Distillation
Author: Team DeepBridge
Author-email: gustavo.haase@gmail.com
Requires-Python: >=3.10,<3.13
Classifier: Development Status :: 5 - Production/Stable
Classifier: Environment :: Console
Classifier: Natural Language :: Portuguese (Brazilian)
Classifier: Programming Language :: Python :: 3
Classifier: Programming Language :: Python :: 3.10
Classifier: Programming Language :: Python :: 3.11
Classifier: Programming Language :: Python :: 3.12
Classifier: Topic :: Scientific/Engineering :: Artificial Intelligence
Requires-Dist: dask[distributed] (>=2023.5.0)
Requires-Dist: jinja2 (>=3.1.0)
Requires-Dist: joblib (>=1.3.0)
Requires-Dist: matplotlib (>=3.7.0)
Requires-Dist: numpy (>=1.24.0,<2.1)
Requires-Dist: onnxruntime (>=1.15.0)
Requires-Dist: optuna (>=3.0.0)
Requires-Dist: pandas (>=2.0.0,<=2.2.2)
Requires-Dist: plotly (>=5.14.0)
Requires-Dist: pyarrow (>=12.0.0)
Requires-Dist: pydantic (>=2.0.0)
Requires-Dist: rich (>=13.0.0)
Requires-Dist: scikit-learn (>=1.3.0)
Requires-Dist: scipy (>=1.11.0)
Requires-Dist: seaborn (>=0.12.0)
Requires-Dist: setuptools (>=65.0.0)
Requires-Dist: statsmodels (>=0.14.0)
Requires-Dist: tabulate (>=0.9.0)
Requires-Dist: typer (>=0.9.0)
Requires-Dist: weasyprint (>=60.0)
Requires-Dist: xgboost (>=2.0.0)
Project-URL: Código, https://github.com/DeepBridge-Validation/DeepBridge
Project-URL: Documentação, https://deepbridge.readthedocs.io/en/latest/
